wherepip.py
wherepip-1.0.8.dist-info/METADATA
wherepip-1.0.8.dist-info/WHEEL
wherepip-1.0.8.dist-info/entry_points.txt
wherepip-1.0.8.dist-info/top_level.txt
wherepip-1.0.8.dist-info/RECORD
