Metadata-Version: 2.1
Name: wherepip
Version: 1.0.8
Summary: 高效python库管理工具,功能有搜索、安装、卸载、获取库所在目录（python学霸公众号）
Home-page: UNKNOWN
Author: Python学霸
Author-email: python@xueba.com
License: UNKNOWN
Platform: UNKNOWN
